excptr/__init__.py
excptr/excptr.py
excptr_karjakak-0.2.7.dist-info/METADATA
excptr_karjakak-0.2.7.dist-info/WHEEL
excptr_karjakak-0.2.7.dist-info/top_level.txt
excptr_karjakak-0.2.7.dist-info/RECORD
